invest/__init__.py
invest/_prep.py
invest/base.py
invest/dacc.py
invest/util.py
invest/misc/__init__.py
invest/misc/quarterly_features.py
invest/misc/yf_prep.py
invest/scripts/__init__.py
invest/scripts/download_yf_data.py
invest-0.1.2.dist-info/LICENSE
invest-0.1.2.dist-info/METADATA
invest-0.1.2.dist-info/WHEEL
invest-0.1.2.dist-info/top_level.txt
invest-0.1.2.dist-info/RECORD
