Metadata-Version: 2.1
Name: invest
Version: 0.1.2
Summary: Python access to structure stock market information
Home-page: https://github.com/thorwhalen/invest
Author: Thor Whalen
License: mit
Keywords: finance,stock market,trading,markets,python,quant,data
Platform: any
License-File: LICENSE
Requires-Dist: dol
Requires-Dist: pandas
Requires-Dist: yfinance
